twitter_ads/__init__.py
twitter_ads/account.py
twitter_ads/analytics.py
twitter_ads/audience.py
twitter_ads/campaign.py
twitter_ads/client.py
twitter_ads/creative.py
twitter_ads/cursor.py
twitter_ads/enum.py
twitter_ads/error.py
twitter_ads/http.py
twitter_ads/resource.py
twitter_ads/restapi.py
twitter_ads/targeting.py
twitter_ads/utils.py
twitter_ads-11.0.0.data/scripts/twitter-ads
twitter_ads-11.0.0.dist-info/LICENSE
twitter_ads-11.0.0.dist-info/METADATA
twitter_ads-11.0.0.dist-info/WHEEL
twitter_ads-11.0.0.dist-info/top_level.txt
twitter_ads-11.0.0.dist-info/RECORD
