Metadata-Version: 2.1
Name: twitter-ads
Version: 11.0.0
Summary: A Twitter supported and maintained Ads API SDK for Python.
Home-page: http://twitterdev.github.io/twitter-python-ads-sdk/
Author: John Babich, Tushar Bhushan, Juan Shishido
Author-email: jbabich@twitter.com, tbhushan@twitter.com, jshishido@twitter.com
License: MIT
Download-URL: https://github.com/twitterdev/twitter-python-ads-sdk/tarball/master
Platform: any
Classifier: Development Status :: 5 - Production/Stable
Classifier: Intended Audience :: Developers
Classifier: License :: OSI Approved :: MIT License
Classifier: Operating System :: OS Independent
Classifier: Programming Language :: Python
Classifier: Programming Language :: Python :: 3
Classifier: Programming Language :: Python :: 3.5
Classifier: Programming Language :: Python :: 3.6
Classifier: Programming Language :: Python :: 3.7
Classifier: Programming Language :: Python :: Implementation :: CPython
Classifier: Programming Language :: Python :: Implementation :: PyPy
Classifier: Topic :: Internet
Classifier: Topic :: Internet :: WWW/HTTP
Classifier: Topic :: Software Development :: Libraries :: Python Modules
License-File: LICENSE
